cv_sample_package/__init__.py
cv_sample_package/cv_sample_add.py
cv_sample_package/cv_sample_aes.py
cv_sample_package/cv_sample_sub.py
cv_sample_package-0.0.1.dist-info/METADATA
cv_sample_package-0.0.1.dist-info/WHEEL
cv_sample_package-0.0.1.dist-info/top_level.txt
cv_sample_package-0.0.1.dist-info/RECORD
