Metadata-Version: 2.1
Name: cv_sample_package
Version: 0.0.1
Summary: A sample test package
Author: Arulvadivel S
Author-email: arulvadivel@cloudvalleytech.com
Requires-Python: >=3.8
Requires-Dist: pycryptodome >=3.19.1
